futurepool/__init__.py
futurepool/futurepool.py
futurepool-1.0.1.dist-info/LICENCE.md
futurepool-1.0.1.dist-info/METADATA
futurepool-1.0.1.dist-info/WHEEL
futurepool-1.0.1.dist-info/RECORD
