Metadata-Version: 2.1
Name: futurepool
Version: 1.0.1
Summary: FuturePool is a package that introduce known concept of multiprocessing Pool to the async/await world, resulting in async workers pool library. It allows for easy translation from multiprocessing to async/await, while keeping the core principle - specified number of workers. FuturePool allows for more flexible usage by providing starimap/starimap_unordered.
License: MIT
Keywords: async/await,worker,pool,scrappig,future,future pool,async pool
Author: Michal Karol
Author-email: michal.p.karol@gmail.com
Requires-Python: >=3.10,<4.0
Classifier: Development Status :: 5 - Production/Stable
Classifier: Framework :: AsyncIO
Classifier: Intended Audience :: Developers
Classifier: License :: OSI Approved :: MIT License
Classifier: Programming Language :: Python :: 3
Classifier: Programming Language :: Python :: 3.10
Classifier: Programming Language :: Python :: 3.11
Classifier: Programming Language :: Python :: 3.12
Classifier: Programming Language :: Python :: 3.13
Classifier: Topic :: Software Development :: Libraries
Requires-Dist: asyncio (>=3.4.3,<4.0.0)
Requires-Dist: pytest (>=8.3.3,<9.0.0)
Requires-Dist: pytest-asyncio (>=0.24.0,<0.25.0)
Requires-Dist: ruff (>=0.7.0,<0.8.0)
Project-URL: Documentation, https://michalkarol.github.io/futurepool/
Project-URL: Homepage, https://michalkarol.github.io/futurepool/
Project-URL: Issues, https://github.com/MichalKarol/futurepool/issues
Project-URL: Repository, https://github.com/MichalKarol/futurepool
Project-URL: Releases, https://github.com/MichalKarol/futurepool/releases
